shpdf_tools/__init__.py
shpdf_tools/convert.py
shpdf_tools/decode.py
shpdf_tools/encode.py
shpdf_tools/error.py
shpdf_tools/format.py
shpdf_tools/reader.py
shpdf_tools-0.1.8.dist-info/LICENSE
shpdf_tools-0.1.8.dist-info/METADATA
shpdf_tools-0.1.8.dist-info/WHEEL
shpdf_tools-0.1.8.dist-info/entry_points.txt
shpdf_tools-0.1.8.dist-info/RECORD
