Metadata-Version: 2.1
Name: shpdf-tools
Version: 0.1.8
Summary: Tools for Slash-Hash Packed Data Format
Home-page: https://github.com/AsherJingkongChen/shpdf-tools/blob/main/README.md
License: MIT
Keywords: data,decode,encode,format,language,parse
Author: AsherJingkongChen
Requires-Python: >=3.9,<4.0
Classifier: License :: OSI Approved :: MIT License
Classifier: Programming Language :: Python :: 3
Classifier: Programming Language :: Python :: 3.9
Classifier: Programming Language :: Python :: 3.10
Classifier: Programming Language :: Python :: 3.11
Classifier: Programming Language :: Python :: 3.12
Requires-Dist: msgspec (>=0.18.6,<0.19.0)
Project-URL: Repository, https://github.com/AsherJingkongChen/shpdf-tools.git
